dragonn/__init__.py
dragonn/calibration.py
dragonn/callbacks.py
dragonn/custom_losses.py
dragonn/dragonn_predict_generator.py
dragonn/generators.py
dragonn/hyperparameter_search_tutorial.py
dragonn/metrics.py
dragonn/models.py
dragonn/positional_prc.py
dragonn/runtime_metrics.py
dragonn/simulations.py
dragonn-0.4.2.dist-info/LICENSE
dragonn-0.4.2.dist-info/METADATA
dragonn-0.4.2.dist-info/WHEEL
dragonn-0.4.2.dist-info/entry_points.txt
dragonn-0.4.2.dist-info/top_level.txt
dragonn-0.4.2.dist-info/RECORD
