Metadata-Version: 2.1
Name: dragonn
Version: 0.4.2
Summary: Deep RegulAtory GenOmic Neural Networks (DragoNN)
Home-page: UNKNOWN
License: UNKNOWN
Platform: UNKNOWN
License-File: LICENSE
Requires-Dist: numpy (>=1.16)
Requires-Dist: keras (==2.3.0)
Requires-Dist: tensorflow-gpu (==1.15)
Requires-Dist: deeplift (>=0.6.9.0)
Requires-Dist: shapely
Requires-Dist: matplotlib (>=3.1.1)
Requires-Dist: plotnine (==0.4.0)
Requires-Dist: scikit-learn (>=0.20.0)
Requires-Dist: pydot-ng (==1.0.0)
Requires-Dist: h5py
Requires-Dist: seqdataloader (>=0.124)
Requires-Dist: simdna-dragonn
Requires-Dist: abstention
